sendmate/__init__.py
sendmate/client.py
sendmate/types.py
sendmate_python-0.1.0.dist-info/METADATA
sendmate_python-0.1.0.dist-info/WHEEL
sendmate_python-0.1.0.dist-info/top_level.txt
sendmate_python-0.1.0.dist-info/RECORD
