Metadata-Version: 2.4
Name: sendmate-python
Version: 0.1.0
Summary: SendMate Python SDK for payment processing and wallet management
Home-page: https://github.com/nextunesolutions/sendmate-python
Author: Nextune Solutions
Author-email: info@nextunesolutions.com
Keywords: payments,mpesa,mpesa api,card payments,visa,mastercard,payments kenya,mpesa stk-push,stk push,sendmate,airtime
Classifier: Development Status :: 3 - Alpha
Classifier: Intended Audience :: Developers
Classifier: License :: OSI Approved :: MIT License
Classifier: Operating System :: OS Independent
Classifier: Programming Language :: Python :: 3
Classifier: Programming Language :: Python :: 3.8
Classifier: Programming Language :: Python :: 3.9
Classifier: Programming Language :: Python :: 3.10
Classifier: Programming Language :: Python :: 3.11
Requires-Python: >=3.8
Requires-Dist: requests>=2.31.0
Requires-Dist: python-dotenv>=1.0.0
Requires-Dist: pydantic>=2.5.0
Dynamic: author
Dynamic: author-email
Dynamic: classifier
Dynamic: description
Dynamic: description-content-type
Dynamic: home-page
Dynamic: keywords
Dynamic: requires-dist
Dynamic: requires-python
Dynamic: summary
